salesforce_tools/__init__.py
salesforce_tools/async_sf/__init__.py
salesforce_tools/async_sf/bulk.py
salesforce_tools/async_sf/client.py
salesforce_tools/async_sf/metadata.py
salesforce_tools/auth.py
salesforce_tools/bulk.py
salesforce_tools/metadata.py
salesforce_tools/models/__init__.py
salesforce_tools/models/bulk.py
salesforce_tools/models/model_factory.py
salesforce_tools/oauth_server.py
salesforce_tools/salesforce.py
salesforce_tools/util.py
salesforce_tools-0.3.8.dist-info/METADATA
salesforce_tools-0.3.8.dist-info/WHEEL
salesforce_tools-0.3.8.dist-info/RECORD
